zssdb.py
zssdb-0.1.2.dist-info/LICENSE
zssdb-0.1.2.dist-info/METADATA
zssdb-0.1.2.dist-info/WHEEL
zssdb-0.1.2.dist-info/top_level.txt
zssdb-0.1.2.dist-info/RECORD
