Metadata-Version: 2.1
Name: zssdb
Version: 0.1.2
Summary: 封装的ssdb连接器
Home-page: https://pypi.org/project/zssdb
Author: zlyuan
Author-email: 1277260932@qq.com
License: GNU GENERAL PUBLIC LICENSE
Platform: all
Classifier: Environment :: Web Environment
Classifier: Intended Audience :: Developers
Classifier: Operating System :: OS Independent
Classifier: Programming Language :: Python
Classifier: Programming Language :: Python :: 3
Requires-Dist: pyssdb
Requires-Dist: zretry
